corrupt/ListFuncs.py
corrupt/__init__.py
corrupt/number.py
corrupt/stringfuncs.py
corrupt-0.1.5.dist-info/METADATA
corrupt-0.1.5.dist-info/WHEEL
corrupt-0.1.5.dist-info/top_level.txt
corrupt-0.1.5.dist-info/RECORD
