Metadata-Version: 2.4
Name: corrupt
Version: 0.1.5
Summary: Corrupt values like strings and numbers in interesting ways.
Author: gootmoney1
Classifier: Programming Language :: Python :: 3
Classifier: Programming Language :: Python :: 3.6
Classifier: Programming Language :: Python :: 3.7
Classifier: Programming Language :: Python :: 3.8
Classifier: Programming Language :: Python :: 3.9
Classifier: Programming Language :: Python :: 3.10
Classifier: Programming Language :: Python :: 3.11
Classifier: Programming Language :: Python :: 3.12
Classifier: Programming Language :: Python :: 3.13
Classifier: License :: OSI Approved :: MIT License
Classifier: Operating System :: OS Independent
Requires-Python: >=3.6,<=3.13.5
Dynamic: author
Dynamic: classifier
Dynamic: description-content-type
Dynamic: requires-python
Dynamic: summary
